Metadata-Version: 1.0
Name: django-timezones-op
Version: 0.2.dev2
Summary: A Django reusable app to deal with timezone localization for users modified for OP
Home-page: http://github.com/OpenProximity/django-timezones/
Author: Manuel Francisco, Brian Rosner
Author-email: manuel@aircable.net, brosner@gmail.com
License: BSD
Platform: UNKNOWN
Classifier: Development Status :: 4 - Beta
Classifier: Environment :: Web Environment
Classifier: Intended Audience :: Developers
Classifier: License :: OSI Approved :: BSD License
Classifier: Operating System :: OS Independent
Classifier: Programming Language :: Python
Classifier: Topic :: Utilities
Classifier: Framework :: Django
